alacritty_circadian/__init__.py
alacritty_circadian/alacritty_circadian.py
alacritty_circadian-0.9.8.dist-info/LICENSE
alacritty_circadian-0.9.8.dist-info/METADATA
alacritty_circadian-0.9.8.dist-info/WHEEL
alacritty_circadian-0.9.8.dist-info/entry_points.txt
alacritty_circadian-0.9.8.dist-info/top_level.txt
alacritty_circadian-0.9.8.dist-info/RECORD
