Metadata-Version: 2.1
Name: alacritty-circadian
Version: 0.9.8
Summary: Alacritty time/sun based theme switch daemon
Home-page: https://github.com/Dr-Dd/alacritty-circadian
Author: Leonardo "drd" Idone
Author-email: idone.leonardo@gmail.com
License: UNKNOWN
Platform: UNKNOWN
Classifier: Programming Language :: Python :: 3 :: Only
Classifier: Programming Language :: Python :: 3.6
Classifier: Programming Language :: Python :: 3.7
Classifier: Programming Language :: Python :: 3.8
Classifier: Programming Language :: Python :: 3.9
Classifier: Programming Language :: Python :: 3.10
Classifier: License :: OSI Approved :: Apache Software License
Classifier: Operating System :: Unix
Classifier: Operating System :: MacOS
Classifier: Operating System :: Microsoft :: Windows
Requires-Python: >=3.6
Requires-Dist: ruamel.yaml
Requires-Dist: astral
Requires-Dist: tzlocal
